dtmd/__init__.py
dtmd/main.py
dtmd-0.1.0.dist-info/METADATA
dtmd-0.1.0.dist-info/WHEEL
dtmd-0.1.0.dist-info/entry_points.txt
dtmd-0.1.0.dist-info/top_level.txt
dtmd-0.1.0.dist-info/RECORD
