Metadata-Version: 2.1
Name: dtmd
Version: 0.1.0
Summary: A tool to convert directory contents to Markdown.
Home-page: https://github.com/adriangalilea/dtm
Author: Adrian Galilea Delgado
Author-email: adriangalilea@gmail.com
Classifier: Programming Language :: Python :: 3
Classifier: License :: OSI Approved :: MIT License
Classifier: Operating System :: OS Independent
Requires-Dist: rich
Requires-Dist: pyperclip
Requires-Dist: fnmatch
